{
    "type": "FeatureCollection",
    "features": [
      {
        "type": "Feature",
        "properties": {},
        "geometry": {
          "type": "Polygon",
          "coordinates": [
            [
              [
                2.3316367136012843,
                49.4037991403909
              ],
              [
                2.251480041260536,
                49.401208961362094
              ],
              [
                2.17212032401299,
                49.39346418410217
              ],
              [
                2.0943458403731254,
                49.380641807113825
              ],
              [
                2.0189276413923243,
                49.362869228757596
              ],
              [
                1.9466112479956263,
                49.34032286282219
              ],
              [
                1.8781087128698863,
                49.31322622851569
              ],
              [
                1.814091154276548,
                49.281847542200836
              ],
              [
                1.755181857825464,
                49.24649684480795
              ],
              [
                1.7019500289992777,
                49.20752270464479
              ],
              [
                1.654905264590568,
                49.165308540179595
              ],
              [
                1.6144927957653645,
                49.12026861123103
              ],
              [
                1.5810895397544942,
                49.07284372982847
              ],
              [
                1.5550009817264274,
                49.02349674381321
              ],
              [
                1.5364588936855006,
                48.972707847076954
              ],
              [
                1.5256198836682815,
                48.92096977024677
              ],
              [
                1.5225647563932658,
                48.86878290471747
              ],
              [
                1.5272986560777913,
                48.81665041131019
              ],
              [
                1.539751953501414,
                48.76507336261891
              ],
              [
                1.5597818326096637,
                48.714545965414175
              ],
              [
                1.5871745269801973,
                48.66555090642612
              ],
              [
                1.6216481532122686,
                48.61855486153886
              ],
              [
                1.6628560865943365,
                48.57400420499847
              ],
              [
                1.7103908240588612,
                48.53232095175566
              ],
              [
                1.7637882802279659,
                48.493898962608284
              ],
              [
                1.8225324640561027,
                48.45910043843623
              ],
              [
                1.8860604859521508,
                48.428252726578435
              ],
              [
                1.95376784808648,
                48.401645459317464
              ],
              [
                2.025013973646158,
                48.37952804152976
              ],
              [
                2.0991279339003333,
                48.3621075018331
              ],
              [
                2.175414334907431,
                48.34954671901368
              ],
              [
                2.2531593283900384,
                48.34196303312732
              ],
              [
                2.3316367136012843,
                48.339427248425594
              ],
              [
                2.4101140988125307,
                48.34196303312732
              ],
              [
                2.487859092295137,
                48.34954671901368
              ],
              [
                2.564145493302236,
                48.3621075018331
              ],
              [
                2.6382594535564103,
                48.37952804152976
              ],
              [
                2.709505579116089,
                48.401645459317464
              ],
              [
                2.777212941250418,
                48.428252726578435
              ],
              [
                2.840740963146466,
                48.45910043843623
              ],
              [
                2.8994851469746026,
                48.493898962608284
              ],
              [
                2.952882603143707,
                48.53232095175566
              ],
              [
                3.0004173406082324,
                48.57400420499847
              ],
              [
                3.0416252739903,
                48.61855486153886
              ],
              [
                3.0760989002223718,
                48.66555090642612
              ],
              [
                3.103491594592905,
                48.714545965414175
              ],
              [
                3.1235214737011545,
                48.76507336261891
              ],
              [
                3.1359747711247774,
                48.81665041131019
              ],
              [
                3.1407086708093033,
                48.86878290471747
              ],
              [
                3.1376535435342876,
                48.92096977024677
              ],
              [
                3.1268145335170683,
                48.972707847076954
              ],
              [
                3.1082724454761412,
                49.02349674381321
              ],
              [
                3.082183887448075,
                49.07284372982847
              ],
              [
                3.048780631437204,
                49.12026861123103
              ],
              [
                3.008368162612001,
                49.165308540179595
              ],
              [
                2.9613233982032914,
                49.20752270464479
              ],
              [
                2.908091569377105,
                49.24649684480795
              ],
              [
                2.849182272926021,
                49.281847542200836
              ],
              [
                2.7851647143326823,
                49.31322622851569
              ],
              [
                2.7166621792069425,
                49.34032286282219
              ],
              [
                2.644345785810244,
                49.362869228757596
              ],
              [
                2.568927586829444,
                49.380641807113825
              ],
              [
                2.4911531031895797,
                49.39346418410217
              ],
              [
                2.4117933859420333,
                49.401208961362094
              ],
              [
                2.3316367136012843,
                49.4037991403909
              ]
            ]
          ]
        }
      },
      {
        "type": "Feature",
        "properties": {},
        "geometry": {
          "type": "Polygon",
          "coordinates": [
            [
              [
                3.1013179758174374,
                50.984304849660106
              ],
              [
                3.0533962401371384,
                50.98281294593856
              ],
              [
                3.0059451481573163,
                50.97835188863385
              ],
              [
                2.9594304512159546,
                50.97096548687978
              ],
              [
                2.914308177655465,
                50.96072624967849
              ],
              [
                2.871019924421595,
                50.94773463329359
              ],
              [
                2.829988328985912,
                50.93211800091037
              ],
              [
                2.791612776171456,
                50.91402930755219
              ],
              [
                2.7562653899674765,
                50.89364552650999
              ],
              [
                2.724287355093047,
                50.87116583649659
              ],
              [
                2.6959856070827595,
                50.84680959133457
              ],
              [
                2.6716299232066287,
                50.82081409619109
              ],
              [
                2.651450439792765,
                50.79343221616053
              ],
              [
                2.6356356146841207,
                50.76492984435823
              ],
              [
                2.624330646808431,
                50.735583257625784
              ],
              [
                2.617636358334625,
                50.70567638847165
              ],
              [
                2.6156085387687136,
                50.67549804200365
              ],
              [
                2.6182577447203905,
                50.64533908637945
              ],
              [
                2.6255495440331718,
                50.615489644742276
              ],
              [
                2.637405188571781,
                50.58623631576196
              ],
              [
                2.6537026962287147,
                50.55785944880619
              ],
              [
                2.6742783196493676,
                50.53063049846422
              ],
              [
                2.6989283767605228,
                50.50480948167777
              ],
              [
                2.727411416379513,
                50.48064255913827
              ],
              [
                2.7594506909243663,
                50.458359760920075
              ],
              [
                2.794736907470364,
                50.43817287456944
              ],
              [
                2.832931228029799,
                50.42027351208186
              ],
              [
                2.8736684898893188,
                50.40483137039982
              ],
              [
                2.91656061704274,
                50.39199269826444
              ],
              [
                2.9612001941286006,
                50.38187898047059
              ],
              [
                3.0071641747481808,
                50.37458584881279
              ],
              [
                3.054017696535345,
                50.37018222727314
              ],
              [
                3.1013179758174374,
                50.36870971729174
              ],
              [
                3.14861825509953,
                50.37018222727314
              ],
              [
                3.1954717768866936,
                50.37458584881279
              ],
              [
                3.2414357575062733,
                50.38187898047059
              ],
              [
                3.2860753345921343,
                50.39199269826444
              ],
              [
                3.328967461745556,
                50.40483137039982
              ],
              [
                3.3697047236050763,
                50.42027351208186
              ],
              [
                3.40789904416451,
                50.43817287456944
              ],
              [
                3.4431852607105076,
                50.458359760920075
              ],
              [
                3.4752245352553612,
                50.48064255913827
              ],
              [
                3.503707574874351,
                50.50480948167777
              ],
              [
                3.5283576319855072,
                50.53063049846422
              ],
              [
                3.54893325540616,
                50.55785944880619
              ],
              [
                3.5652307630630937,
                50.58623631576196
              ],
              [
                3.5770864076017026,
                50.615489644742276
              ],
              [
                3.5843782069144847,
                50.64533908637945
              ],
              [
                3.5870274128661612,
                50.67549804200365
              ],
              [
                3.584999593300249,
                50.70567638847165
              ],
              [
                3.578305304826444,
                50.735583257625784
              ],
              [
                3.567000336950754,
                50.76492984435823
              ],
              [
                3.55118551184211,
                50.79343221616053
              ],
              [
                3.531006028428246,
                50.82081409619109
              ],
              [
                3.506650344552116,
                50.84680959133457
              ],
              [
                3.478348596541828,
                50.87116583649659
              ],
              [
                3.4463705616673983,
                50.89364552650999
              ],
              [
                3.4110231754634186,
                50.91402930755219
              ],
              [
                3.372647622648963,
                50.93211800091037
              ],
              [
                3.33161602721328,
                50.94773463329359
              ],
              [
                3.2883277739794097,
                50.96072624967849
              ],
              [
                3.2432055004189206,
                50.97096548687978
              ],
              [
                3.1966908034775585,
                50.97835188863385
              ],
              [
                3.1492397114977364,
                50.98281294593856
              ],
              [
                3.1013179758174374,
                50.984304849660106
              ]
            ]
          ]
        }
      },
      {
        "type": "Feature",
        "properties": {},
        "geometry": {
          "type": "Polygon",
          "coordinates": [
            [
              [
                -0.5380214907269476,
                45.43288808678544
              ],
              [
                -0.6175621812558918,
                45.4301183606126
              ],
              [
                -0.6963137775108932,
                45.42183666684986
              ],
              [
                -0.7734957079823895,
                45.40812516236241
              ],
              [
                -0.8483443258421205,
                45.389119788179805
              ],
              [
                -0.9201210721221997,
                45.365008803682294
              ],
              [
                -0.988120288053254,
                45.336030763689344
              ],
              [
                -1.0516765728304687,
                45.30247196680177
              ],
              [
                -1.110171593684075,
                45.26466341024227
              ],
              [
                -1.1630402675437026,
                45.222977292500715
              ],
              [
                -1.2097762473175295,
                45.17782311021074
              ],
              [
                -1.249936660342875,
                45.1296433997935
              ],
              [
                -1.283146061390173,
                45.07890917746726
              ],
              [
                -1.3090995772287253,
                45.026115133243685
              ],
              [
                -1.3275652337499022,
                44.97177463555002
              ],
              [
                -1.3383854696172326,
                44.916414603196145
              ],
              [
                -1.3414778520762307,
                44.8605703006367
              ],
              [
                -1.336835020697021,
                44.80478011096699
              ],
              [
                -1.3245238933115002,
                44.74958033895211
              ],
              [
                -1.3046841751960794,
                44.69550009374284
              ],
              [
                -1.277526217665884,
                44.643056297897395
              ],
              [
                -1.243328275773508,
                44.592748866017025
              ],
              [
                -1.2024332168816356,
                44.545056092819365
              ],
              [
                -1.1552447326776345,
                44.50043028690575
              ],
              [
                -1.102223106917345,
                44.45929368290318
              ],
              [
                -1.0438805900352837,
                44.42203466114052
              ],
              [
                -0.9807764299522701,
                44.389004300596994
              ],
              [
                -0.9135116061562718,
                44.3605132875716
              ],
              [
                -0.842723311622619,
                44.336829199384916
              ],
              [
                -0.7690792245531659,
                44.318174179445414
              ],
              [
                -0.6932716094073776,
                44.30472301719034
              ],
              [
                -0.6160112844065462,
                44.29660164373427
              ],
              [
                -0.5380214907269477,
                44.29388605150902
              ],
              [
                -0.4600316970473491,
                44.29660164373427
              ],
              [
                -0.3827713720465178,
                44.30472301719034
              ],
              [
                -0.3069637569007294,
                44.318174179445414
              ],
              [
                -0.2333196698312767,
                44.336829199384916
              ],
              [
                -0.16253137529762374,
                44.3605132875716
              ],
              [
                -0.09526655150162494,
                44.389004300596994
              ],
              [
                -0.032162391418611797,
                44.42203466114052
              ],
              [
                0.02618012546344964,
                44.45929368290318
              ],
              [
                0.0792017512237393,
                44.50043028690575
              ],
              [
                0.12639023542774022,
                44.545056092819365
              ],
              [
                0.16728529431961248,
                44.592748866017025
              ],
              [
                0.20148323621198866,
                44.643056297897395
              ],
              [
                0.22864119374218417,
                44.69550009374284
              ],
              [
                0.24848091185760507,
                44.74958033895211
              ],
              [
                0.2607920392431257,
                44.80478011096699
              ],
              [
                0.26543487062233545,
                44.8605703006367
              ],
              [
                0.26234248816333755,
                44.916414603196145
              ],
              [
                0.2515222522960068,
                44.97177463555002
              ],
              [
                0.23305659577482993,
                45.026115133243685
              ],
              [
                0.20710307993627755,
                45.07890917746726
              ],
              [
                0.17389367888897972,
                45.1296433997935
              ],
              [
                0.1337332658636345,
                45.17782311021074
              ],
              [
                0.08699728608980734,
                45.222977292500715
              ],
              [
                0.03412861223018012,
                45.26466341024227
              ],
              [
                -0.024366408623426202,
                45.30247196680177
              ],
              [
                -0.08792269340064113,
                45.336030763689344
              ],
              [
                -0.15592190933169525,
                45.365008803682294
              ],
              [
                -0.22769865561177494,
                45.389119788179805
              ],
              [
                -0.30254727347150484,
                45.40812516236241
              ],
              [
                -0.37972920394300164,
                45.42183666684986
              ],
              [
                -0.4584808001980034,
                45.4301183606126
              ],
              [
                -0.5380214907269476,
                45.43288808678544
              ]
            ]
          ]
        }
      },
      {
        "type": "Feature",
        "properties": {},
        "geometry": {
          "type": "Polygon",
          "coordinates": [
            [
              [
                5.302596107076994,
                43.81533536238576
              ],
              [
                5.233953409399764,
                43.812881520495466
              ],
              [
                5.16598846420229,
                43.80554422812888
              ],
              [
                5.099371832901817,
                43.79339592771327
              ],
              [
                5.034759791583176,
                43.776556501836886
              ],
              [
                4.9727874281385525,
                43.755192003214226
              ],
              [
                4.9140620211693316,
                43.729512900651926
              ],
              [
                4.859156784816265,
                43.699771864370675
              ],
              [
                4.8086050558155655,
                43.66626111980115
              ],
              [
                4.762894989823935,
                43.62930940410167
              ],
              [
                4.722464823752379,
                43.5892785640578
              ],
              [
                4.687698749856958,
                43.54655983765465
              ],
              [
                4.658923436018447,
                43.501569864433236
              ],
              [
                4.636405215352801,
                43.45474647174157
              ],
              [
                4.620347957352407,
                43.40654428519202
              ],
              [
                4.610891622444309,
                43.35743021207649
              ],
              [
                4.608111492396378,
                43.3078788462304
              ],
              [
                4.612018060579321,
                43.258367841946935
              ],
              [
                4.62255755881803,
                43.20937330310545
              ],
              [
                4.639613091499713,
                43.16136523178152
              ],
              [
                4.663006342756087,
                43.11480307833431
              ],
              [
                4.692499818863893,
                43.07013143240934
              ],
              [
                4.727799585435008,
                43.027775891526204
              ],
              [
                4.768558457386889,
                42.98813914101742
              ],
              [
                4.814379598966922,
                42.95159727610452
              ],
              [
                4.86482049110761,
                42.918496393896554
              ],
              [
                4.919397223964511,
                42.889149480113176
              ],
              [
                4.97758907348681,
                42.863833612403155
              ],
              [
                5.038843322148171,
                42.84278749926832
              ],
              [
                5.102580285390056,
                42.82620937082778
              ],
              [
                5.168198506780469,
                42.81425523497006
              ],
              [
                5.235080086263173,
                42.8070375098403
              ],
              [
                5.302596107076994,
                42.80462404108759
              ],
              [
                5.370112127890815,
                42.8070375098403
              ],
              [
                5.436993707373519,
                42.81425523497006
              ],
              [
                5.502611928763932,
                42.82620937082778
              ],
              [
                5.566348892005816,
                42.84278749926832
              ],
              [
                5.627603140667178,
                42.863833612403155
              ],
              [
                5.685794990189477,
                42.889149480113176
              ],
              [
                5.740371723046378,
                42.918496393896554
              ],
              [
                5.790812615187066,
                42.95159727610452
              ],
              [
                5.836633756767099,
                42.98813914101742
              ],
              [
                5.8773926287189795,
                43.027775891526204
              ],
              [
                5.912692395290096,
                43.07013143240934
              ],
              [
                5.942185871397902,
                43.11480307833431
              ],
              [
                5.965579122654276,
                43.16136523178152
              ],
              [
                5.982634655335958,
                43.20937330310545
              ],
              [
                5.9931741535746665,
                43.258367841946935
              ],
              [
                5.99708072175761,
                43.3078788462304
              ],
              [
                5.9943005917096785,
                43.35743021207649
              ],
              [
                5.984844256801581,
                43.40654428519202
              ],
              [
                5.968786998801187,
                43.45474647174157
              ],
              [
                5.946268778135542,
                43.501569864433236
              ],
              [
                5.9174934642970305,
                43.54655983765465
              ],
              [
                5.882727390401611,
                43.5892785640578
              ],
              [
                5.8422972243300535,
                43.62930940410167
              ],
              [
                5.796587158338422,
                43.66626111980115
              ],
              [
                5.746035429337723,
                43.699771864370675
              ],
              [
                5.691130192984657,
                43.729512900651926
              ],
              [
                5.632404786015436,
                43.755192003214226
              ],
              [
                5.5704324225708115,
                43.776556501836886
              ],
              [
                5.505820381252172,
                43.79339592771327
              ],
              [
                5.439203749951699,
                43.80554422812888
              ],
              [
                5.371238804754223,
                43.812881520495466
              ],
              [
                5.302596107076994,
                43.81533536238576
              ]
            ]
          ]
        }
      }
    ]
  }